[
  {
    "question": "\\( \\mathrm{A}_{2}(\\mathrm{~g})+3 \\mathrm{~B}_{2}(\\mathrm{~g}) \\rightleftharpoons 2 \\mathrm{AB}_{3}(\\mathrm{~g}) \\)  বিক্রিয়ার ক্ষেত্রে-i. চাপ বৃদ্ধি করলে উৎপাদ বাড়বেii. A₂ যোগ করলে উৎপাদ বাড়বেiii.  \\( \\mathrm{K}_{\\mathrm{p}} ও \\mathrm{K}_{\\mathrm{c}} \\)  সমান হবেনিচের কোনটি সঠিক?",
    "image": null,
    "options": [
      "",
      "",
      "",
      ""
    ],
    "answer": "খ"
  },
  {
    "question": "\\( \\mathrm{~K}_{4}\\left[\\mathrm{Fe}(\\mathrm{CN})_{6}\\right] \\)  বিকারকটি দিয়ে কোন আয়নটি শনাক্ত করা যায়?",
    "image": null,
    "options": [
      " \\( \\mathrm{Cu}^{2+} \\) ",
      " \\( \\mathrm{Al}^{3+} \\) ",
      " \\( \\mathrm{Na}^{+} \\) ",
      " \\( \\mathrm{NH}_{4}^{+} \\) "
    ],
    "answer": "ক"
  },
  {
    "question": "A+ ফ্রুক্টোজ ——ইস্ট থেকে উৎপন্ন/প্রভাবক—→উৎপাদ + CO2বিক্রিয়াটিতে-i. A হলো শর্করাii. প্রভাবক হলো জাইমেজiii. উৎপাদটি জ্বালানি হিসেবে ব্যবহৃত হয়নিচের কোনটি সঠিক?",
    "image": null,
    "options": [
      "i ও ii",
      "ii ও iii",
      "i ও iii",
      "i, ii ও iii"
    ],
    "answer": "ঘ"
  },
  {
    "question": "বোর পরমাণু মডেল ব্যাখ্যা করতে পারে-i.  \\( \\mathrm{Be}^{2+} \\)  আয়নের বর্ণালিii. ধাপান্তরিত ইলেকট্রনের শক্তি শোষণ ও বিকিরণiii. পরমাণুর স্থায়িত্বনিচের কোনটি সঠিক?",
    "image": null,
    "options": [
      "",
      "",
      "i ও iii",
      ""
    ],
    "answer": "খ"
  },
  {
    "question": "ইলেকট্রন আসক্তির সঠিক ক্রম কোনটি?",
    "image": null,
    "options": [
      " \\( \\mathrm{S}>\\mathrm{O}>\\mathrm{Se}>\\mathrm{Te}>\\mathrm{Po} \\) ",
      " \\( \\mathrm{Se}>\\mathrm{Te}>\\mathrm{Po}>\\mathrm{O}>\\mathrm{S} \\) ",
      " \\( \\mathrm{O}>\\mathrm{S}>\\mathrm{Se}>\\mathrm{Te}>\\mathrm{Po} \\) ",
      " \\( \\mathrm{S}>\\mathrm{Se}>\\mathrm{Te}>\\mathrm{Po}>\\mathrm{O} \\) "
    ],
    "answer": "ঘ"
  },
  {
    "question": "\\( 1 \\%\\left(\\frac{W}{V}\\right) \\mathrm{NaOH} \\)  দ্রবণের  \\( \\mathrm{PH}^{\\mathrm{PH}} \\)  কত?",
    "image": null,
    "options": [
      "13.39",
      "12.25",
      "1.00",
      ""
    ],
    "answer": "ক"
  },
  {
    "question": "কোনটি দুর্বল লিগ্যান্ড?",
    "image": null,
    "options": [
      "  \\( \\mathrm{NH}_{3} \\) ",
      " \\( \\mathrm{F}^{-} \\) ",
      "CO",
      " \\( \\mathrm{CN}^{-} \\) "
    ],
    "answer": "খ"
  },
  {
    "question": "Fe এর ২২তম ইলেকট্রনের জন্য চারটি কোয়ান্টাম সংখ্যার সঠিক সেট কোনটি?",
    "image": null,
    "options": [
      " \\( n=3, l=2, m=-1, s=+\\frac{1}{2} \\) ",
      " \\( n=3, l=1, m=-1, s=+\\frac{1}{2} \\) ",
      " \\( n=3, l=2, m=-2, s=-\\frac{1}{2} \\) ",
      " \\( n=3, l=1, m=-2, s=-\\frac{1}{2} \\) "
    ],
    "answer": "ক"
  },
  {
    "question": "\\( \\mathrm{Al}_{2}\\left(\\mathrm{SO}_{4}\\right)_{3} \\)  এয় দ্রাব্যতা গুণফল  \\( 1.5 \\times 10^{-5} \\)  হলে ।  \\( \\mathrm{SO}_{4}^{2-} \\)  এর মোলার ঘনমাত্রা কত ?",
    "image": null,
    "options": [
      " \\( 1.27 \\times 10^{-1} \\mathrm{M} \\) ",
      " \\( 4.20 \\times 10^{-2} \\mathrm{M} \\) ",
      " \\( 6.21 \\times 10^{-3} \\mathrm{M} \\) ",
      " \\( 6.02 \\times 10^{-3} \\mathrm{M} \\) "
    ],
    "answer": "ক"
  },
  {
    "question": "কত তাপমাত্রার  \\( \\mathrm{PCl}_{5}(\\mathrm{~g}) \\rightleftharpoons \\mathrm{PCl}_{3}(\\mathrm{~g})+\\mathrm{Cl}_{2}(\\mathrm{~g}) \\)  বিক্রিয়ার  \\( K_{P}ও K_{C} \\)  পরস্পর সমান হবে?",
    "image": null,
    "options": [
      "0.1218 K",
      "0.1218°C",
      "12.18K",
      ""
    ],
    "answer": "গ"
  },
  {
    "question": "কোন লবণটির পানিতে দ্রাব্যতার উপর তাপমাত্রার ব্যতিক্রমী প্রভাব বিদ্যমান?",
    "image": null,
    "options": [
      " \\( \\mathrm{Na}_{2} \\mathrm{SO}_{4}-10 \\mathrm{H}_{2} \\mathrm{O} \\) ",
      " \\( \\mathrm{KNO}_{3} \\) ",
      "NaCl",
      " \\( \\mathrm{CuSO}_{4} \\cdot \\mathrm{5H}_{2} \\mathrm{O} \\) "
    ],
    "answer": "ক"
  },
  {
    "question": "কোনটির মধ্যে ইলেকট্রন ও নিউট্রন সংখ্যা সমান?",
    "image": null,
    "options": [
      " \\( { }_{9}^{19} \\mathrm{~F}^{-} \\) ",
      " \\( { }_{8}^{16} \\mathrm{O}^{2-} \\) ",
      " \\( { }_{7}^{14} \\mathrm{~N}^{3-} \\) ",
      " \\( { }_{4}^{9} \\mathrm{Be} \\) "
    ],
    "answer": "ক"
  },
  {
    "question": "কোনটির পোলারায়ন করার ক্ষমতা বেশি?",
    "image": null,
    "options": [
      " \\( \\mathrm{Ca}^{2+} \\) ",
      " \\( \\mathrm{Ba}^{2+} \\) ",
      " \\( \\mathrm{Al}^{3+} \\) ",
      " \\( \\mathrm{Fe}^{3+} \\) "
    ],
    "answer": "গ"
  },
  {
    "question": "অম্লীয় বাফার দ্রবণের pH নির্ণয়ের সমীকরণ কোনটি?",
    "image": null,
    "options": [
      " \\( \\mathrm{P}^{\\mathrm{H}}=\\mathrm{PK}_{\\mathrm{a}}-lo\\mathrm{~g} \\frac{\\text { [লবণ] }}{\\text { [ক্ষার] }} \\) ",
      " \\( \\mathrm{PH}^{\\mathrm{H}}=\\mathrm{PK}_{\\mathrm{a}}+10 \\mathrm{~g} \\frac{\\text { [লবণ] }}{\\text { [ক্ষার] }} \\) ",
      " \\( P^{H }=P K_{a}-lo g \\frac{\\text { [লবণ] }}{\\text { [এসিড] }} \\) ",
      " \\( P^{H}=P K_{a}+lo g \\frac{\\text { [লবণ] }}{\\text { [এসিড] }} \\) "
    ],
    "answer": "ঘ"
  },
  {
    "question": "কোন রশ্মিটির শক্তি সবচেয়ে বেশি?",
    "image": null,
    "options": [
      "UV-রশ্মি",
      "IR-রশ্মি",
      " \\(  \\gamma \\) -রশ্মি",
      " \\( \\alpha \\) -রশ্মি"
    ],
    "answer": "গ"
  },
  {
    "question": "কোনটি এন্টি-অক্সিডেন্ট?",
    "image": null,
    "options": [
      " \\( \\mathrm{C}_{6} \\mathrm{H}_{8} \\mathrm{O}_{2} \\) ",
      "EDTA",
      "",
      " \\( \\mathrm{K}_{2} \\mathrm{~S}_{2} \\mathrm{O}_{5} \\) "
    ],
    "answer": "গ"
  },
  {
    "question": "পটাশিয়াম এর সর্বশেষ ইলেকট্রনটির কৌণিক ভরবেগ কত?",
    "image": null,
    "options": [
      " \\( 3.42 \\times 10^{-32} \\mathrm{JS} \\) ",
      "4.22  \\( \\times 10^{-34} \\mathrm{JS} \\) ",
      " \\( 3.64 \\times 10^{-27} \\mathrm{JS} \\) ",
      " \\( 4.22 \\times 10^{-28} \\mathrm{JS} \\) "
    ],
    "answer": "খ"
  },
  {
    "question": "এখানে প্রতীকসমূহ ধরে নেয়া হয়েছে, প্রকৃত নয়।কোনটিতে বন্ধন কোণ সর্বনিম্ন?",
    "image": "https://assets.chorcha.net/WL09lg9Al9z9v79L969eW.png",
    "options": [
      "",
      " \\( \\mathrm{LA}_{3} \\) ",
      " \\( \\mathrm{BA}_{3} \\) ",
      " \\( \\mathrm{A}_{2} \\mathrm{X} \\) "
    ],
    "answer": "ক"
  },
  {
    "question": "অসওয়াল্ড লঘুকরণ সূত্রানুসারে বিয়োজন মাত্রার ক্ষেত্রে কোনটি সঠিক?",
    "image": null,
    "options": [
      " \\( \\alpha \\propto \\mathrm{C} \\) ",
      " \\( \\alpha \\propto \\frac{1}{\\sqrt{c}} \\) ",
      " \\( \\alpha \\propto \\frac{1}{\\mathrm{C}} \\) ",
      " \\( \\alpha \\propto \\mathrm{C}^{2} \\) "
    ],
    "answer": "খ"
  },
  {
    "question": "\\( \\left[\\mathrm{Cu}\\left(\\mathrm{NH}_{3}\\right)_{4}\\right] \\mathrm{SO}_{4} \\)  এয় কেন্দ্রীয় আয়নের সংকরণ কীরূপ?",
    "image": null,
    "options": [
      " \\( s p^{3} d \\) ",
      " \\( s p^{3} d^{2} \\) ",
      " \\( s p^{2} d^{2} \\) ",
      " \\( s p^{2} d \\) "
    ],
    "answer": "ঘ"
  },
  {
    "question": "কোন জোড়া দ্রবণ থেকে ক্ষারীয় বাফার দ্রবণ তৈরি করা যাবে?i.  \\( \\mathrm{HCOOH}+\\mathrm{NH}_{4} \\mathrm{OH} \\) ii.  \\( \\mathrm{HNO}_{3}+\\mathrm{NH}_{4} \\mathrm{OH} \\) iii.  \\( \\mathrm{HCOOH}+\\mathrm{KOH} \\) নিচের কোনটি সঠিক?",
    "image": null,
    "options": [
      "",
      "i ও ii",
      "",
      ""
    ],
    "answer": null
  },
  {
    "question": "কোনটি ভিনেগার?",
    "image": null,
    "options": [
      "  \\( \\mathrm{CH}_{3} \\mathrm{CH}_{2} \\mathrm{OH} \\)  এর 96.4% জলীয় দ্রবণ",
      "HCOOH ",
      " \\( \\mathrm{CH}_{3} \\mathrm{COOH} \\)  ",
      ""
    ],
    "answer": "গ"
  },
  {
    "question": "কোনটি ডায়াম্যাগনেটিক ধাতু?",
    "image": null,
    "options": [
      "Fe",
      "",
      "",
      ""
    ],
    "answer": "ঘ"
  },
  {
    "question": "এখানে প্রতীকসমূহ ধরে নেয়া হয়েছে, প্রকৃত নয়। \\( \\mathrm{YM}_{6} \\)  যৌগের ক্ষেত্রে প্রযোজ্য- i. এটি  \\( \\mathrm{sp}^{3} \\mathrm{~d}^{2} \\) সংকরিত ii. এটি অষ্টতলকীয়iii. এতে বন্ধন কোণ 120°নিচের কোনটি সঠিক?",
    "image": "https://assets.chorcha.net/ouxEXrBqZ5dNAe3FFAq7t.png",
    "options": [
      "",
      "ii ও iii",
      "i ও iii",
      ""
    ],
    "answer": "ক"
  },
  {
    "question": "\\( \\mathrm{PH}_{4}^{+} \\) আয়নে কী কী ধরনের বন্ধন বিদ্যমান?",
    "image": null,
    "options": [
      "",
      "",
      "",
      ""
    ],
    "answer": "গ"
  }
]